README.md
setup.py
blockchain/__init__.py
blockchain/client.py
blockchain/network.py
blockchainpy.egg-info/PKG-INFO
blockchainpy.egg-info/SOURCES.txt
blockchainpy.egg-info/dependency_links.txt
blockchainpy.egg-info/not-zip-safe
blockchainpy.egg-info/requires.txt
blockchainpy.egg-info/top_level.txt