Metadata-Version: 2.1
Name: blockchainpy
Version: 0.0.4
Summary: A blockchain implementation in Python
Home-page: https://github.com/rishikant42/blockchain
Author: Rishi kant
Author-email: rshkntshrm@gmail.com
License: MIT
Platform: UNKNOWN
